jto/__init__.py
jto/dataclass_generator.py
jto/json_builder.py
jto/json_parser.py
jto/undefined_field.py
jto-1.4.0.dist-info/LICENSE.md
jto-1.4.0.dist-info/METADATA
jto-1.4.0.dist-info/WHEEL
jto-1.4.0.dist-info/top_level.txt
jto-1.4.0.dist-info/RECORD
