Metadata-Version: 2.1
Name: jto
Version: 1.4.0
Summary: Convert json object to dataclass and vice versa
Author-email: l0kifs <l0kifs91@gmail.com>
License: Apache License
Project-URL: Homepage, https://github.com/l0kifs/jto_converter
Keywords: json,object,converter
Classifier: License :: OSI Approved :: Apache Software License
Classifier: Programming Language :: Python
Classifier: Programming Language :: Python :: 3
Requires-Python: >=3.9
License-File: LICENSE.md
Provides-Extra: dev
Requires-Dist: pip-tools ; extra == 'dev'
Requires-Dist: pytest ; extra == 'dev'
